[{"name":"前端","path":"api/categories/前端.json","slug":"前端","count":13},{"name":"jenkins部署","path":"api/categories/jenkins部署.json","slug":"jenkins部署","count":1},{"name":"问题记录","path":"api/categories/问题记录.json","slug":"问题记录","count":3},{"name":"Vue","path":"api/categories/Vue.json","slug":"Vue","count":2},{"name":"自检清单","path":"api/categories/前端/自检清单.json","slug":"前端/自检清单","count":13},{"name":"Vue","path":"api/categories/前端/自检清单/Vue.json","slug":"前端/自检清单/Vue","count":2},{"name":"JS","path":"api/categories/前端/自检清单/JS.json","slug":"前端/自检清单/JS","count":10},{"name":"nginx","path":"api/categories/nginx.json","slug":"nginx","count":1},{"name":"Hexo","path":"api/categories/Hexo.json","slug":"Hexo","count":1}]